latexipy/__init__.py
latexipy/_latexipy.py
latexipy-1.0.1.dist-info/DESCRIPTION.rst
latexipy-1.0.1.dist-info/METADATA
latexipy-1.0.1.dist-info/RECORD
latexipy-1.0.1.dist-info/WHEEL
latexipy-1.0.1.dist-info/metadata.json
latexipy-1.0.1.dist-info/top_level.txt
