Metadata-Version: 2.0
Name: latexipy
Version: 1.0.1
Summary: Generate beautiful plots for LaTeX using your existing matplotlib-based code.
Home-page: https://github.com/masasin/latexipy
Author: Jean Nassar
Author-email: jn.masasin@gmail.com
License: MIT license
Keywords: latexipy
Platform: UNKNOWN
Classifier: Development Status :: 2 - Pre-Alpha
Classifier: Intended Audience :: Developers
Classifier: License :: OSI Approved :: MIT License
Classifier: Natural Language :: English
Classifier: Programming Language :: Python :: 3
Classifier: Programming Language :: Python :: 3.6
Requires-Dist: matplotlib
